Workbook

Sheet Assumptions
A1: PROJECT FINANCIAL ASSUMPTIONS
A2: CMA & Loan Sanction Sensitivity Baseline
A3: Core Assumptions & Growth Driver
A4: Parameter | B4: Year 1 (Y1) | C4: Year 2 (Y2) | D4: Year 3 (Y3) | E4: Year 4 (Y4) | F4: Year 5 (Y5)
A5: Capacity Utilization % | B5: 0.6 | C5: 0.7 | D5: 0.8 | E5: 0.9 | F5: 0.95
A7: Sales Growth % (YoY) | B7: 0.1 | C7: 0.15 | D7: 0.12 | E7: 0.1 | F7: 0.08
A9: Raw Material Cost % of Sales | B9: 0.55 | C9: 0.54 | D9: 0.535 | E9: 0.53 | F9: 0.53
A11: Other Operating Expenses % of Sales | B11: 0.12 | C11: 0.115 | D11: 0.11 | E11: 0.105 | F11: 0.105
A14: Loan Sanction Parameters
A15: Sanction Parameter | B15: Assumed Baseline Value
A16: Term Loan Sanctioned (₹) | B16: 15000000
A17: CC Limit Sanctioned (₹) | B17: 8000000
A18: Term Loan Interest Rate (per Annum) | B18: 0.105
A19: Cash Credit Interest Rate (per Annum) | B19: 0.115
A20: Repayment Term (Months) | B20: 60
A21: Moratorium Period (Months) | B21: 6
A22: Corporate Income Tax Rate | B22: 0.2517
A23: CC Stock Margin % | B23: 0.25
A24: CC Debtors Margin % | B24: 0.4
A27: Fixed Asset Blocks & Depreciation Rates (WDV)
A28: Asset Block Class | B28: Starting Net Block Value (₹) | C28: Depreciation Rate (WDV)
A29: Building Block | B29: 3941803.2 | C29: 0.1
A30: Plant & Machinery Block | B30: 4927254 | C30: 0.15
A31: Computers & IT Block | B31: 492725.4 | C31: 0.4
A32: Office Equipment Block | B32: 492725.4 | C32: 0.1
A35: Preceding Year (Base) Financials
A36: Base Year Revenue (₹) | B36: 12894723
A37: Initial Share Capital (₹) | B37: 11860499
A38: Initial Cash Balance (₹) | B38: 193420.85

Sheet Repayment
A1: TERM LOAN REPAYMENT SCHEDULE
A2: Monthly Amortization and Yearly Aggregations
A3: Monthly Loan Amortization Schedule
A4: Month | B4: Opening Balance | C4: Interest Accrued | D4: Principal Repayment | E4: Total EMI | F4: Closing Balance | H4: Yearly Summary Schedule
A5: 1 | B5: =Assumptions!$B$16 | C5: =B5*(Assumptions!$B$18/12) | D5: =IF(A5<=Assumptions!$B$21,0,Assumptions!$B$16/(Assumptions!$B$20-Assumptions!$B$21)) | E5: =C5+D5 | F5: =B5-D5 | H5: Year | I5: Opening Balance | J5: Interest Sum | K5: Principal Sum | L5: Total Debt Service | M5: Closing Balance
A6: 2 | B6: =F5 | C6: =B6*(Assumptions!$B$18/12) | D6: =IF(A6<=Assumptions!$B$21,0,Assumptions!$B$16/(Assumptions!$B$20-Assumptions!$B$21)) | E6: =C6+D6 | F6: =B6-D6 | H6: 1 | I6: =B5 | J6: =SUM(C5:C16) | K6: =SUM(D5:D16) | L6: =J6+K6 | M6: =F16
A7: 3 | B7: =F6 | C7: =B7*(Assumptions!$B$18/12) | D7: =IF(A7<=Assumptions!$B$21,0,Assumptions!$B$16/(Assumptions!$B$20-Assumptions!$B$21)) | E7: =C7+D7 | F7: =B7-D7 | H7: 2 | I7: =B17 | J7: =SUM(C17:C28) | K7: =SUM(D17:D28) | L7: =J7+K7 | M7: =F28
A8: 4 | B8: =F7 | C8: =B8*(Assumptions!$B$18/12) | D8: =IF(A8<=Assumptions!$B$21,0,Assumptions!$B$16/(Assumptions!$B$20-Assumptions!$B$21)) | E8: =C8+D8 | F8: =B8-D8 | H8: 3 | I8: =B29 | J8: =SUM(C29:C40) | K8: =SUM(D29:D40) | L8: =J8+K8 | M8: =F40
A9: 5 | B9: =F8 | C9: =B9*(Assumptions!$B$18/12) | D9: =IF(A9<=Assumptions!$B$21,0,Assumptions!$B$16/(Assumptions!$B$20-Assumptions!$B$21)) | E9: =C9+D9 | F9: =B9-D9 | H9: 4 | I9: =B41 | J9: =SUM(C41:C52) | K9: =SUM(D41:D52) | L9: =J9+K9 | M9: =F52
A10: 6 | B10: =F9 | C10: =B10*(Assumptions!$B$18/12) | D10: =IF(A10<=Assumptions!$B$21,0,Assumptions!$B$16/(Assumptions!$B$20-Assumptions!$B$21)) | E10: =C10+D10 | F10: =B10-D10 | H10: 5 | I10: =B53 | J10: =SUM(C53:C64) | K10: =SUM(D53:D64) | L10: =J10+K10 | M10: =F64
A11: 7 | B11: =F10 | C11: =B11*(Assumptions!$B$18/12) | D11: =IF(A11<=Assumptions!$B$21,0,Assumptions!$B$16/(Assumptions!$B$20-Assumptions!$B$21)) | E11: =C11+D11 | F11: =B11-D11
A12: 8 | B12: =F11 | C12: =B12*(Assumptions!$B$18/12) | D12: =IF(A12<=Assumptions!$B$21,0,Assumptions!$B$16/(Assumptions!$B$20-Assumptions!$B$21)) | E12: =C12+D12 | F12: =B12-D12
A13: 9 | B13: =F12 | C13: =B13*(Assumptions!$B$18/12) | D13: =IF(A13<=Assumptions!$B$21,0,Assumptions!$B$16/(Assumptions!$B$20-Assumptions!$B$21)) | E13: =C13+D13 | F13: =B13-D13
A14: 10 | B14: =F13 | C14: =B14*(Assumptions!$B$18/12) | D14: =IF(A14<=Assumptions!$B$21,0,Assumptions!$B$16/(Assumptions!$B$20-Assumptions!$B$21)) | E14: =C14+D14 | F14: =B14-D14
A15: 11 | B15: =F14 | C15: =B15*(Assumptions!$B$18/12) | D15: =IF(A15<=Assumptions!$B$21,0,Assumptions!$B$16/(Assumptions!$B$20-Assumptions!$B$21)) | E15: =C15+D15 | F15: =B15-D15
A16: 12 | B16: =F15 | C16: =B16*(Assumptions!$B$18/12) | D16: =IF(A16<=Assumptions!$B$21,0,Assumptions!$B$16/(Assumptions!$B$20-Assumptions!$B$21)) | E16: =C16+D16 | F16: =B16-D16
A17: 13 | B17: =F16 | C17: =B17*(Assumptions!$B$18/12) | D17: =IF(A17<=Assumptions!$B$21,0,Assumptions!$B$16/(Assumptions!$B$20-Assumptions!$B$21)) | E17: =C17+D17 | F17: =B17-D17
A18: 14 | B18: =F17 | C18: =B18*(Assumptions!$B$18/12) | D18: =IF(A18<=Assumptions!$B$21,0,Assumptions!$B$16/(Assumptions!$B$20-Assumptions!$B$21)) | E18: =C18+D18 | F18: =B18-D18
A19: 15 | B19: =F18 | C19: =B19*(Assumptions!$B$18/12) | D19: =IF(A19<=Assumptions!$B$21,0,Assumptions!$B$16/(Assumptions!$B$20-Assumptions!$B$21)) | E19: =C19+D19 | F19: =B19-D19
A20: 16 | B20: =F19 | C20: =B20*(Assumptions!$B$18/12) | D20: =IF(A20<=Assumptions!$B$21,0,Assumptions!$B$16/(Assumptions!$B$20-Assumptions!$B$21)) | E20: =C20+D20 | F20: =B20-D20
A21: 17 | B21: =F20 | C21: =B21*(Assumptions!$B$18/12) | D21: =IF(A21<=Assumptions!$B$21,0,Assumptions!$B$16/(Assumptions!$B$20-Assumptions!$B$21)) | E21: =C21+D21 | F21: =B21-D21
A22: 18 | B22: =F21 | C22: =B22*(Assumptions!$B$18/12) | D22: =IF(A22<=Assumptions!$B$21,0,Assumptions!$B$16/(Assumptions!$B$20-Assumptions!$B$21)) | E22: =C22+D22 | F22: =B22-D22
... A64: 60 | B64: =F63 | C64: =B64*(Assumptions!$B$18/12) | D64: =IF(A64<=Assumptions!$B$21,0,Assumptions!$B$16/(Assumptions!$B$20-Assumptions!$B$21)) | E64: =C64+D64 | F64: =B64-D64

Sheet Depreciation
A1: FIXED ASSETS & DEPRECIATION SCHEDULE
A2: WDV Capital Allowance and Asset Additions Registry
A3: Building Block
A4: Year | B4: Opening WDV | C4: Additions (>180d) | D4: Additions (<180d) | E4: Deletions | F4: Gross Block | G4: Depreciation | H4: Closing Net Block
A5: 1 | B5: 3941803.2 | C5: 0 | D5: 0 | E5: 0 | F5: =B5+C5+D5-E5 | G5: =(B5+C5-E5)*Assumptions!$C$29+D5*Assumptions!$C$29*0.5 | H5: =F5-G5
A6: 2 | B6: =H5 | C6: 0 | D6: 0 | E6: 0 | F6: =B6+C6+D6-E6 | G6: =(B6+C6-E6)*Assumptions!$C$29+D6*Assumptions!$C$29*0.5 | H6: =F6-G6
A7: 3 | B7: =H6 | C7: 0 | D7: 0 | E7: 0 | F7: =B7+C7+D7-E7 | G7: =(B7+C7-E7)*Assumptions!$C$29+D7*Assumptions!$C$29*0.5 | H7: =F7-G7
A8: 4 | B8: =H7 | C8: 0 | D8: 0 | E8: 0 | F8: =B8+C8+D8-E8 | G8: =(B8+C8-E8)*Assumptions!$C$29+D8*Assumptions!$C$29*0.5 | H8: =F8-G8
A9: 5 | B9: =H8 | C9: 0 | D9: 0 | E9: 0 | F9: =B9+C9+D9-E9 | G9: =(B9+C9-E9)*Assumptions!$C$29+D9*Assumptions!$C$29*0.5 | H9: =F9-G9
A12: Plant & Machinery Block
A13: Year | B13: Opening WDV | C13: Additions (>180d) | D13: Additions (<180d) | E13: Deletions | F13: Gross Block | G13: Depreciation | H13: Closing Net Block
A14: 1 | B14: 4927254 | C14: 0 | D14: 0 | E14: 0 | F14: =B14+C14+D14-E14 | G14: =(B14+C14-E14)*Assumptions!$C$30+D14*Assumptions!$C$30*0.5 | H14: =F14-G14
A15: 2 | B15: =H14 | C15: 0 | D15: 0 | E15: 0 | F15: =B15+C15+D15-E15 | G15: =(B15+C15-E15)*Assumptions!$C$30+D15*Assumptions!$C$30*0.5 | H15: =F15-G15
A16: 3 | B16: =H15 | C16: 0 | D16: 0 | E16: 0 | F16: =B16+C16+D16-E16 | G16: =(B16+C16-E16)*Assumptions!$C$30+D16*Assumptions!$C$30*0.5 | H16: =F16-G16
A17: 4 | B17: =H16 | C17: 0 | D17: 0 | E17: 0 | F17: =B17+C17+D17-E17 | G17: =(B17+C17-E17)*Assumptions!$C$30+D17*Assumptions!$C$30*0.5 | H17: =F17-G17
A18: 5 | B18: =H17 | C18: 0 | D18: 0 | E18: 0 | F18: =B18+C18+D18-E18 | G18: =(B18+C18-E18)*Assumptions!$C$30+D18*Assumptions!$C$30*0.5 | H18: =F18-G18
A21: Computers & IT Block
A22: Year | B22: Opening WDV | C22: Additions (>180d) | D22: Additions (<180d) | E22: Deletions | F22: Gross Block | G22: Depreciation | H22: Closing Net Block
A23: 1 | B23: 492725.4 | C23: 0 | D23: 0 | E23: 0 | F23: =B23+C23+D23-E23 | G23: =(B23+C23-E23)*Assumptions!$C$31+D23*Assumptions!$C$31*0.5 | H23: =F23-G23
A24: 2 | B24: =H23 | C24: 0 | D24: 0 | E24: 0 | F24: =B24+C24+D24-E24 | G24: =(B24+C24-E24)*Assumptions!$C$31+D24*Assumptions!$C$31*0.5 | H24: =F24-G24
A25: 3 | B25: =H24 | C25: 0 | D25: 0 | E25: 0 | F25: =B25+C25+D25-E25 | G25: =(B25+C25-E25)*Assumptions!$C$31+D25*Assumptions!$C$31*0.5 | H25: =F25-G25
A26: 4 | B26: =H25 | C26: 0 | D26: 0 | E26: 0 | F26: =B26+C26+D26-E26 | G26: =(B26+C26-E26)*Assumptions!$C$31+D26*Assumptions!$C$31*0.5 | H26: =F26-G26
A27: 5 | B27: =H26 | C27: 0 | D27: 0 | E27: 0 | F27: =B27+C27+D27-E27 | G27: =(B27+C27-E27)*Assumptions!$C$31+D27*Assumptions!$C$31*0.5 | H27: =F27-G27
A30: Office Equipment Block
A31: Year | B31: Opening WDV | C31: Additions (>180d) | D31: Additions (<180d) | E31: Deletions | F31: Gross Block | G31: Depreciation | H31: Closing Net Block
A32: 1 | B32: 492725.4 | C32: 0 | D32: 0 | E32: 0 | F32: =B32+C32+D32-E32 | G32: =(B32+C32-E32)*Assumptions!$C$32+D32*Assumptions!$C$32*0.5 | H32: =F32-G32
A33: 2 | B33: =H32 | C33: 0 | D33: 0 | E33: 0 | F33: =B33+C33+D33-E33 | G33: =(B33+C33-E33)*Assumptions!$C$32+D33*Assumptions!$C$32*0.5 | H33: =F33-G33
A34: 3 | B34: =H33 | C34: 0 | D34: 0 | E34: 0 | F34: =B34+C34+D34-E34 | G34: =(B34+C34-E34)*Assumptions!$C$32+D34*Assumptions!$C$32*0.5 | H34: =F34-G34
A35: 4 | B35: =H34 | C35: 0 | D35: 0 | E35: 0 | F35: =B35+C35+D35-E35 | G35: =(B35+C35-E35)*Assumptions!$C$32+D35*Assumptions!$C$32*0.5 | H35: =F35-G35
A36: 5 | B36: =H35 | C36: 0 | D36: 0 | E36: 0 | F36: =B36+C36+D36-E36 | G36: =(B36+C36-E36)*Assumptions!$C$32+D36*Assumptions!$C$32*0.5 | H36: =F36-G36
A39: CONSOLIDATED FIXED ASSETS SUMMARY
A40: Year | B40: Opening Net Block | C40: Total Additions | D40: Total Deletions | E40: Gross Consolidated Block | F40: Total Depreciation | G40: Net Closing Block
A41: 1 | B41: =B5+B14+B23+B32 | C41: =C5+D5+C14+D14+C23+D23+C32+D32 | D41: =E5+E14+E23+E32 | E41: =F5+F14+F23+F32 | F41: =G5+G14+G23+G32 | G41: =H5+H14+H23+H32
A42: 2 | B42: =B6+B15+B24+B33 | C42: =C6+D6+C15+D15+C24+D24+C33+D33 | D42: =E6+E15+E24+E33 | E42: =F6+F15+F24+F33 | F42: =G6+G15+G24+G33 | G42: =H6+H15+H24+H33
A43: 3 | B43: =B7+B16+B25+B34 | C43: =C7+D7+C16+D16+C25+D25+C34+D34 | D43: =E7+E16+E25+E34 | E43: =F7+F16+F25+F34 | F43: =G7+G16+G25+G34 | G43: =H7+H16+H25+H34
A44: 4 | B44: =B8+B17+B26+B35 | C44: =C8+D8+C17+D17+C26+D26+C35+D35 | D44: =E8+E17+E26+E35 | E44: =F8+F17+F26+F35 | F44: =G8+G17+G26+G35 | G44: =H8+H17+H26+H35
A45: 5 | B45: =B9+B18+B27+B36 | C45: =C9+D9+C18+D18+C27+D27+C36+D36 | D45: =E9+E18+E27+E36 | E45: =F9+F18+F27+F36 | F45: =G9+G18+G27+G36 | G45: =H9+H18+H27+H36

Sheet Projected P&L
A1: PROJECTED STATEMENT OF PROFIT & LOSS (₹)
A2: 5-Year Profitability Forecast & Margin Trajectory
A4: Particulars | B4: Base Year (Y0) | C4: Year 1 (Y1) | D4: Year 2 (Y2) | E4: Year 3 (Y3) | F4: Year 4 (Y4) | G4: Year 5 (Y5)
A5: Capacity Utilization % | B5: - | C5: Assumptions!B5 | D5: Assumptions!C5 | E5: Assumptions!D5 | F5: Assumptions!E5 | G5: Assumptions!F5
A6: Revenue from Sales | B6: Assumptions!$B$36 | C6: =B6*(1+Assumptions!B7) | D6: =C6*(1+Assumptions!C7) | E6: =D6*(1+Assumptions!D7) | F6: =E6*(1+Assumptions!E7) | G6: =F6*(1+Assumptions!F7)
A7: Less: Cost of Materials Consumed (RM) | B7: 24750000 | C7: =C6*Assumptions!B9 | D7: =D6*Assumptions!C9 | E7: =E6*Assumptions!D9 | F7: =F6*Assumptions!E9 | G7: =G6*Assumptions!F9
A8: Less: Power, Labor & Administrative Exp | B8: 5400000 | C8: =C6*Assumptions!B11 | D8: =D6*Assumptions!C11 | E8: =E6*Assumptions!D11 | F8: =F6*Assumptions!E11 | G8: =G6*Assumptions!F11
A9: Earnings before EBITDA | B9: =B6-B7-B8 | C9: =C6-C7-C8 | D9: =D6-D7-D8 | E9: =E6-E7-E8 | F9: =F6-F7-F8 | G9: =G6-G7-G8
A10: Less: Depreciation & Amortization | B10: 4100000 | C10: =Depreciation!F41 | D10: =Depreciation!F42 | E10: =Depreciation!F43 | F10: =Depreciation!F44 | G10: =Depreciation!F45
A11: Operating Profit (EBIT) | B11: =B9-B10 | C11: =C9-C10 | D11: =D9-D10 | E11: =E9-E10 | F11: =F9-F10 | G11: =G9-G10
A12: Less: Term Loan Interest Expenses | B12: 0 | C12: =Repayment!$J$6 | D12: =Repayment!$J$7 | E12: =Repayment!$J$8 | F12: =Repayment!$J$9 | G12: =Repayment!$J$10
A13: Less: Cash Credit Interest Expenses | B13: 0 | C13: ='Balance Sheet'!C12*Assumptions!$B$19 | D13: ='Balance Sheet'!D12*Assumptions!$B$19 | E13: ='Balance Sheet'!E12*Assumptions!$B$19 | F13: ='Balance Sheet'!F12*Assumptions!$B$19 | G13: ='Balance Sheet'!G12*Assumptions!$B$19
A14: Total Interest Expenses | B14: =B12+B13 | C14: =C12+C13 | D14: =D12+D13 | E14: =E12+E13 | F14: =F12+F13 | G14: =G12+G13
A15: Profit Before Taxes (PBT) | B15: =B11-B14 | C15: =C11-C14 | D15: =D11-D14 | E15: =E11-E14 | F15: =F11-F14 | G15: =G11-G14
A16: Less: Tax Provision | B16: 0 | C16: =IF(C15>0,C15*Assumptions!$B$22,0) | D16: =IF(D15>0,D15*Assumptions!$B$22,0) | E16: =IF(E15>0,E15*Assumptions!$B$22,0) | F16: =IF(F15>0,F15*Assumptions!$B$22,0) | G16: =IF(G15>0,G15*Assumptions!$B$22,0)
A17: Net Profit After Tax (PAT) | B17: =B15-B16 | C17: =C15-C16 | D17: =D15-D16 | E17: =E15-E16 | F17: =F15-F16 | G17: =G15-G16

Sheet MPBF
A1: WORKING CAPITAL Gap & MPBF ASSESSMENT
A2: Tandon Committee (Second Method) Calculations
A4: Particulars | B4: Year 1 (Y1) | C4: Year 2 (Y2) | D4: Year 3 (Y3) | E4: Year 4 (Y4) | F4: Year 5 (Y5)
A5: Current Assets (CA) for Assessment | B5: ='Balance Sheet'!C20+'Balance Sheet'!C21+'Balance Sheet'!C23+Assumptions!$B$38 | C5: ='Balance Sheet'!D20+'Balance Sheet'!D21+'Balance Sheet'!D23+Assumptions!$B$38 | D5: ='Balance Sheet'!E20+'Balance Sheet'!E21+'Balance Sheet'!E23+Assumptions!$B$38 | E5: ='Balance Sheet'!F20+'Balance Sheet'!F21+'Balance Sheet'!F23+Assumptions!$B$38 | F5: ='Balance Sheet'!G20+'Balance Sheet'!G21+'Balance Sheet'!G23+Assumptions!$B$38
A6: Less: Current Liabilities (excluding bank borrowings) | B6: ='Balance Sheet'!C13+'Balance Sheet'!C14 | C6: ='Balance Sheet'!D13+'Balance Sheet'!D14 | D6: ='Balance Sheet'!E13+'Balance Sheet'!E14 | E6: ='Balance Sheet'!F13+'Balance Sheet'!F14 | F6: ='Balance Sheet'!G13+'Balance Sheet'!G14
A7: Working Capital Gap (WCG) | B7: =B4-B5 | C7: =C4-C5 | D7: =D4-D5 | E7: =E4-E5 | F7: =F4-F5
A8: Promoter Margin / Min Net Working Capital (25% of CA) | B8: =0.25*B4 | C8: =0.25*C4 | D8: =0.25*D4 | E8: =0.25*E4 | F8: =0.25*F4
A9: Max Permissible Bank Finance (MPBF) = WCG - Margin | B9: =MAX(0,B6-B7) | C9: =MAX(0,C6-C7) | D9: =MAX(0,D6-D7) | E9: =MAX(0,E6-E7) | F9: =MAX(0,F6-F7)
A10: Actual Net Working Capital (NWC) = CA - Total CL | B10: =B4-('Balance Sheet'!C12+'Balance Sheet'!C13+'Balance Sheet'!C14) | C10: =C4-('Balance Sheet'!D12+'Balance Sheet'!D13+'Balance Sheet'!D14) | D10: =D4-('Balance Sheet'!E12+'Balance Sheet'!E13+'Balance Sheet'!E14) | E10: =E4-('Balance Sheet'!F12+'Balance Sheet'!F13+'Balance Sheet'!F14) | F10: =F4-('Balance Sheet'!G12+'Balance Sheet'!G13+'Balance Sheet'!G14)
A11: Cash Credit Finance Required (Assumed) | B11: =MIN(Assumptions!$B$17,B9) | C11: =MIN(Assumptions!$B$17,C9) | D11: =MIN(Assumptions!$B$17,D9) | E11: =MIN(Assumptions!$B$17,E9) | F11: =MIN(Assumptions!$B$17,F9)

Sheet Balance Sheet
A1: PROJECTED BALANCE SHEET (₹)
A2: 5-Year Capital Structure and Financial Position Statement
A4: Particulars | B4: Base Year (Y0) | C4: Year 1 (Y1) | D4: Year 2 (Y2) | E4: Year 3 (Y3) | F4: Year 4 (Y4) | G4: Year 5 (Y5)
A5: EQUITY AND LIABILITIES
A6: 1. Shareholders' Funds
A7: - Share Capital | B7: =Assumptions!$B$37 | C7: =B7 | D7: =C7 | E7: =D7 | F7: =E7 | G7: =F7
A8: - Reserves & Surplus (Retained Profit) | B8: 3500000 | C8: =B8+'Projected P&L'!C17 | D8: =C8+'Projected P&L'!D17 | E8: =D8+'Projected P&L'!E17 | F8: =E8+'Projected P&L'!F17 | G8: =F8+'Projected P&L'!G17
A9: 2. Non-Current Liabilities
A10: - Long-Term Borrowings (Term Loan) | B10: 0 | C10: =Repayment!$M$6 | D10: =Repayment!$M$7 | E10: =Repayment!$M$8 | F10: =Repayment!$M$9 | G10: =Repayment!$M$10
A11: 3. Current Liabilities
A12: - Short-Term Borrowings (Cash Credit) | B12: 0 | C12: ='MPBF'!B11 | D12: ='MPBF'!C11 | E12: ='MPBF'!D11 | F12: ='MPBF'!E11 | G12: ='MPBF'!F11
A13: - Sundry Creditors (Trade Payables) | B13: 3500000 | C13: ='Projected P&L'!C7*0.082 | D13: ='Projected P&L'!D7*0.082 | E13: ='Projected P&L'!E7*0.082 | F13: ='Projected P&L'!F7*0.082 | G13: ='Projected P&L'!G7*0.082
A14: - Other Current Liabilities | B14: 1500000 | C14: =B13*1.05 | D14: =C13*1.05 | E14: =D13*1.05 | F14: =E13*1.05 | G14: =F13*1.05
A15: TOTAL EQUITY & LIABILITIES | B15: =B7+B8+B10+B12+B13+B14 | C15: =C7+C8+C10+C12+C13+C14 | D15: =D7+D8+D10+D12+D13+D14 | E15: =E7+E8+E10+E12+E13+E14 | F15: =F7+F8+F10+F12+F13+F14 | G15: =G7+G8+G10+G12+G13+G14
A16: ASSETS
A17: 1. Non-Current Assets
A18: - Fixed Assets (Net Block) | B18: 41000000 | C18: =Depreciation!G41 | D18: =Depreciation!G42 | E18: =Depreciation!G43 | F18: =Depreciation!G44 | G18: =Depreciation!G45
A19: 2. Current Assets
A20: - Inventories (Stock) | B20: 11000000 | C20: ='Projected P&L'!C7*0.22 | D20: ='Projected P&L'!D7*0.22 | E20: ='Projected P&L'!E7*0.22 | F20: ='Projected P&L'!F7*0.22 | G20: ='Projected P&L'!G7*0.22
A21: - Trade Receivables (Debtors) | B21: 10000000 | C21: ='Projected P&L'!C6*0.16 | D21: ='Projected P&L'!D6*0.16 | E21: ='Projected P&L'!E6*0.16 | F21: ='Projected P&L'!F6*0.16 | G21: ='Projected P&L'!G6*0.16
A22: - Cash & Bank Balances | B22: =Assumptions!$B$38 | C22: ='Cash Flow'!B23 | D22: ='Cash Flow'!C23 | E22: ='Cash Flow'!D23 | F22: ='Cash Flow'!E23 | G22: ='Cash Flow'!F23
A23: - Other Current Assets | B23: 1000000 | C23: =B22*1.03 | D23: =C22*1.03 | E23: =D22*1.03 | F23: =E22*1.03 | G23: =F22*1.03
A24: TOTAL ASSETS | B24: =B18+B20+B21+B22+B23 | C24: =C18+C20+C21+C22+C23 | D24: =D18+D20+D21+D22+D23 | E24: =E18+E20+E21+E22+E23 | F24: =F18+F20+F21+F22+F23 | G24: =G18+G20+G21+G22+G23
A25: Balance Sheet Audit Check (Diff) | B25: =B24-B15 | C25: =C24-C15 | D25: =D24-D15 | E25: =E24-E15 | F25: =F24-F15 | G25: =G24-G15

Sheet Cash Flow
A1: PROJECTED CASH FLOW STATEMENT (₹)
A2: Sources and Applications of Capital Funds
A4: Particulars | B4: Year 1 (Y1) | C4: Year 2 (Y2) | D4: Year 3 (Y3) | E4: Year 4 (Y4) | F4: Year 5 (Y5)
A5: A. SOURCES OF FUNDS
A6: - Profit After Tax (PAT) | B6: ='Projected P&L'!C17 | C6: ='Projected P&L'!D17 | D6: ='Projected P&L'!E17 | E6: ='Projected P&L'!F17 | F6: ='Projected P&L'!G17
A7: - Add: Depreciation & Amortization | B7: ='Projected P&L'!C10 | C7: ='Projected P&L'!D10 | D7: ='Projected P&L'!E10 | E7: ='Projected P&L'!F10 | F7: ='Projected P&L'!G10
A8: - Term Loan Disbursement | B8: =Assumptions!$B$16 | C8: 0 | D8: 0 | E8: 0 | F8: 0
A9: - CC Borrowing Increase | B9: ='Balance Sheet'!C12-'Balance Sheet'!B12 | C9: ='Balance Sheet'!D12-'Balance Sheet'!C12 | D9: ='Balance Sheet'!E12-'Balance Sheet'!D12 | E9: ='Balance Sheet'!F12-'Balance Sheet'!E12 | F9: ='Balance Sheet'!G12-'Balance Sheet'!F12
A10: - Increase in Sundry Creditors | B10: =MAX(0,'Balance Sheet'!C13-'Balance Sheet'!B13) | C10: =MAX(0,'Balance Sheet'!D13-'Balance Sheet'!C13) | D10: =MAX(0,'Balance Sheet'!E13-'Balance Sheet'!B13) | E10: =MAX(0,'Balance Sheet'!F13-'Balance Sheet'!E13) | F10: =MAX(0,'Balance Sheet'!G13-'Balance Sheet'!F13)
A11: - Increase in Other Current Liabilities | B11: =MAX(0,'Balance Sheet'!C14-'Balance Sheet'!B14) | C11: =MAX(0,'Balance Sheet'!D14-'Balance Sheet'!C14) | D11: =MAX(0,'Balance Sheet'!E14-'Balance Sheet'!D14) | E11: =MAX(0,'Balance Sheet'!F14-'Balance Sheet'!E14) | F11: =MAX(0,'Balance Sheet'!G14-'Balance Sheet'!F14)
A12: TOTAL SOURCES OF FUNDS (A) | B12: =SUM(B6:B11) | C12: =SUM(C6:C11) | D12: =SUM(D6:D11) | E12: =SUM(E6:E11) | F12: =SUM(F6:F11)
A13: B. APPLICATIONS OF FUNDS
A14: - Capital Expenditures (Capex) | B14: =Depreciation!C41 | C14: =Depreciation!C42 | D14: =Depreciation!C43 | E14: =Depreciation!C44 | F14: =Depreciation!C45
A15: - Repayment of Term Loan Principal | B15: =Repayment!K6 | C15: =Repayment!K7 | D15: =Repayment!K8 | E15: =Repayment!K9 | F15: =Repayment!K10
A16: - Increase in Inventories (Working Cap) | B16: =MAX(0,'Balance Sheet'!C20-'Balance Sheet'!B20) | C16: =MAX(0,'Balance Sheet'!D20-'Balance Sheet'!C20) | D16: =MAX(0,'Balance Sheet'!E20-'Balance Sheet'!D20) | E16: =MAX(0,'Balance Sheet'!F20-'Balance Sheet'!E20) | F16: =MAX(0,'Balance Sheet'!G20-'Balance Sheet'!F20)
A17: - Increase in Trade Receivables | B17: =MAX(0,'Balance Sheet'!C21-'Balance Sheet'!B21) | C17: =MAX(0,'Balance Sheet'!D21-'Balance Sheet'!C21) | D17: =MAX(0,'Balance Sheet'!E21-'Balance Sheet'!D21) | E17: =MAX(0,'Balance Sheet'!F21-'Balance Sheet'!E21) | F17: =MAX(0,'Balance Sheet'!G21-'Balance Sheet'!F21)
A18: - Decrease in Sundry Creditors | B18: =MAX(0,'Balance Sheet'!B13-'Balance Sheet'!C13) | C18: =MAX(0,'Balance Sheet'!C13-'Balance Sheet'!D13) | D18: =MAX(0,'Balance Sheet'!D13-'Balance Sheet'!E13) | E18: =MAX(0,'Balance Sheet'!E13-'Balance Sheet'!F13) | F18: =MAX(0,'Balance Sheet'!F13-'Balance Sheet'!G13)
A19: - Decrease in Other Current Liabilities | B19: =MAX(0,'Balance Sheet'!B14-'Balance Sheet'!C14) | C19: =MAX(0,'Balance Sheet'!C14-'Balance Sheet'!D14) | D19: =MAX(0,'Balance Sheet'!D14-'Balance Sheet'!E14) | E19: =MAX(0,'Balance Sheet'!E14-'Balance Sheet'!F14) | F19: =MAX(0,'Balance Sheet'!F14-'Balance Sheet'!G14)
A20: TOTAL APPLICATIONS OF FUNDS (B) | B20: =SUM(B14:B19) | C20: =SUM(C14:C19) | D20: =SUM(D14:D19) | E20: =SUM(E14:E19) | F20: =SUM(F14:F19)
A21: C. NET CASH FLOW (A - B) | B21: =B12-B20 | C21: =C12-C20 | D21: =D12-D20 | E21: =E12-E20 | F21: =F12-F20
A22: Opening Cash & Bank Balance | B22: =Assumptions!$B$38 | C22: =B23 | D22: =C23 | E22: =D23 | F22: =E23
A23: Closing Cash & Bank Balance | B23: =B21+B22 | C23: =C21+C22 | D23: =D21+D22 | E23: =E21+E22 | F23: =F21+F22

Sheet Drawing Power
A1: CASH CREDIT DRAWING POWER STATEMENT
A2: Stipulated Banking Margins against Paid-up Stocks and Eligible Receivables
A4: Particulars | B4: Year 1 (Y1) | C4: Year 2 (Y2) | D4: Year 3 (Y3) | E4: Year 4 (Y4) | F4: Year 5 (Y5)
A5: Total Inventories (Stock) | B5: ='Balance Sheet'!C20 | C5: ='Balance Sheet'!D20 | D5: ='Balance Sheet'!E20 | E5: ='Balance Sheet'!F20 | F5: ='Balance Sheet'!G20
A6: Less: Sundry Creditors for RM | B6: ='Balance Sheet'!C13 | C6: ='Balance Sheet'!D13 | D6: ='Balance Sheet'!E13 | E6: ='Balance Sheet'!F13 | F6: ='Balance Sheet'!G13
A7: Paid-up Stock (A) | B7: =B5-B6 | C7: =C5-C6 | D7: =D5-D6 | E7: =E5-E6 | F7: =F5-F6
A8: Less: Stipulated Margin on Stock (Assumptions!B23) | B8: =B7*Assumptions!$B$23 | C8: =C7*Assumptions!$B$23 | D8: =D7*Assumptions!$B$23 | E8: =E7*Assumptions!$B$23 | F8: =F7*Assumptions!$B$23
A9: Drawing Power on Inventory (B) | B9: =B7-B8 | C9: =C7-C8 | D9: =D7-D8 | E9: =E7-E8 | F9: =F7-F8
A10: Total Debtors (Receivables) | B10: ='Balance Sheet'!C21 | C10: ='Balance Sheet'!D21 | D10: ='Balance Sheet'!E21 | E10: ='Balance Sheet'!F21 | F10: ='Balance Sheet'!G21
A11: Eligible Receivables (< 90 Days) (C) | B11: =B10*0.85 | C11: =C10*0.85 | D11: =D10*0.85 | E11: =E10*0.85 | F11: =F10*0.85
A12: Less: Stipulated Margin on Debtors (Assumptions!B24) | B12: =B11*Assumptions!$B$24 | C12: =C11*Assumptions!$B$24 | D12: =D11*Assumptions!$B$24 | E12: =E11*Assumptions!$B$24 | F12: =F11*Assumptions!$B$24
A13: Drawing Power on Debtors (D) | B13: =B11-B12 | C13: =C11-C12 | D13: =D11-D12 | E13: =E11-E12 | F13: =F11-F12
A14: Total Drawing Power (DP) = B + D | B14: =B9+B13 | C14: =C9+C13 | D14: =D9+D13 | E14: =E9+E13 | F14: =F9+F13
A15: CC Sanctioned Limit | B15: =Assumptions!$B$17 | C15: =Assumptions!$B$17 | D15: =Assumptions!$B$17 | E15: =Assumptions!$B$17 | F15: =Assumptions!$B$17
A16: Effective Allowed Bank CC Borrowing | B16: =MIN(B14,B15) | C16: =MIN(C14,C15) | D16: =MIN(D14,D15) | E16: =MIN(E14,E15) | F16: =MIN(F14,F15)

Sheet Dashboard
A1: FINANCIAL ANALYSIS DASHBOARD
A2: Key Leverage, Profitability & Repayment Ratios
A4: Key Ratio / Indicator | B4: Year 1 (Y1) | C4: Year 2 (Y2) | D4: Year 3 (Y3) | E4: Year 4 (Y4) | F4: Year 5 (Y5)
A5: Current Ratio (CA / CL) | B5: =('Balance Sheet'!C20+'Balance Sheet'!C21+'Balance Sheet'!C22+'Balance Sheet'!C23)/('Balance Sheet'!C11+'Balance Sheet'!C12+'Balance Sheet'!C13+'Balance Sheet'!C14) | C5: =('Balance Sheet'!D20+'Balance Sheet'!D21+'Balance Sheet'!D22+'Balance Sheet'!D23)/('Balance Sheet'!D11+'Balance Sheet'!D12+'Balance Sheet'!D13+'Balance Sheet'!D14) | D5: =('Balance Sheet'!E20+'Balance Sheet'!E21+'Balance Sheet'!E22+'Balance Sheet'!E23)/('Balance Sheet'!E11+'Balance Sheet'!E12+'Balance Sheet'!E13+'Balance Sheet'!E14) | E5: =('Balance Sheet'!F20+'Balance Sheet'!F21+'Balance Sheet'!F22+'Balance Sheet'!F23)/('Balance Sheet'!F11+'Balance Sheet'!F12+'Balance Sheet'!F13+'Balance Sheet'!F14) | F5: =('Balance Sheet'!G20+'Balance Sheet'!G21+'Balance Sheet'!G22+'Balance Sheet'!G23)/('Balance Sheet'!G11+'Balance Sheet'!G12+'Balance Sheet'!G13+'Balance Sheet'!G14)
A6: Quick Ratio (Quick Assets / CL) | B6: =('Balance Sheet'!C21+'Balance Sheet'!C22+'Balance Sheet'!C23)/('Balance Sheet'!C11+'Balance Sheet'!C12+'Balance Sheet'!C13+'Balance Sheet'!C14) | C6: =('Balance Sheet'!D21+'Balance Sheet'!D22+'Balance Sheet'!D23)/('Balance Sheet'!D11+'Balance Sheet'!D12+'Balance Sheet'!D13+'Balance Sheet'!D14) | D6: =('Balance Sheet'!E21+'Balance Sheet'!E22+'Balance Sheet'!E23)/('Balance Sheet'!E11+'Balance Sheet'!E12+'Balance Sheet'!E13+'Balance Sheet'!E14) | E6: =('Balance Sheet'!F21+'Balance Sheet'!F22+'Balance Sheet'!F23)/('Balance Sheet'!F11+'Balance Sheet'!F12+'Balance Sheet'!F13+'Balance Sheet'!F14) | F6: =('Balance Sheet'!G21+'Balance Sheet'!G22+'Balance Sheet'!G23)/('Balance Sheet'!G11+'Balance Sheet'!G12+'Balance Sheet'!G13+'Balance Sheet'!G14)
A7: Debt-Equity Ratio (Total Debt / Equity) | B7: =('Balance Sheet'!C10+'Balance Sheet'!C12)/('Balance Sheet'!C7+'Balance Sheet'!C8) | C7: =('Balance Sheet'!D10+'Balance Sheet'!D12)/('Balance Sheet'!D7+'Balance Sheet'!D8) | D7: =('Balance Sheet'!E10+'Balance Sheet'!E12)/('Balance Sheet'!E7+'Balance Sheet'!E8) | E7: =('Balance Sheet'!F10+'Balance Sheet'!F12)/('Balance Sheet'!F7+'Balance Sheet'!F8) | F7: =('Balance Sheet'!G10+'Balance Sheet'!G12)/('Balance Sheet'!G7+'Balance Sheet'!G8)
A8: Debt Service Coverage Ratio (DSCR) | B8: =IF((Repayment!$K$6+'Projected P&L'!C12)>0,('Projected P&L'!C17+'Projected P&L'!C10+'Projected P&L'!C12)/(Repayment!$K$6+'Projected P&L'!C12),0) | C8: =IF((Repayment!$K$7+'Projected P&L'!D12)>0,('Projected P&L'!D17+'Projected P&L'!D10+'Projected P&L'!D12)/(Repayment!$K$7+'Projected P&L'!D12),0) | D8: =IF((Repayment!$K$8+'Projected P&L'!E12)>0,('Projected P&L'!E17+'Projected P&L'!E10+'Projected P&L'!E12)/(Repayment!$K$8+'Projected P&L'!E12),0) | E8: =IF((Repayment!$K$9+'Projected P&L'!F12)>0,('Projected P&L'!F17+'Projected P&L'!F10+'Projected P&L'!F12)/(Repayment!$K$9+'Projected P&L'!F12),0) | F8: =IF((Repayment!$K$10+'Projected P&L'!G12)>0,('Projected P&L'!G17+'Projected P&L'!G10+'Projected P&L'!G12)/(Repayment!$K$10+'Projected P&L'!G12),0)
A9: Interest Coverage Ratio (ISCR) | B9: =IF('Projected P&L'!C14>0,'Projected P&L'!C11/'Projected P&L'!C14,0) | C9: =IF('Projected P&L'!D14>0,'Projected P&L'!D11/'Projected P&L'!D14,0) | D9: =IF('Projected P&L'!E14>0,'Projected P&L'!E11/'Projected P&L'!E14,0) | E9: =IF('Projected P&L'!F14>0,'Projected P&L'!F11/'Projected P&L'!F14,0) | F9: =IF('Projected P&L'!G14>0,'Projected P&L'!G11/'Projected P&L'!G14,0)
A10: Gross Profit Margin % | B10: ='Projected P&L'!C9/'Projected P&L'!C6 | C10: ='Projected P&L'!D9/'Projected P&L'!D6 | D10: ='Projected P&L'!E9/'Projected P&L'!E6 | E10: ='Projected P&L'!F9/'Projected P&L'!F6 | F10: ='Projected P&L'!G9/'Projected P&L'!G6
A11: Net Profit Margin % | B11: ='Projected P&L'!C17/'Projected P&L'!C6 | C11: ='Projected P&L'!D17/'Projected P&L'!D6 | D11: ='Projected P&L'!E17/'Projected P&L'!E6 | E11: ='Projected P&L'!F17/'Projected P&L'!F6 | F11: ='Projected P&L'!G17/'Projected P&L'!G6
A14: RISK ASSESSMENT & BANKING REPRICING EVALUATIONS
A15: Evaluation Area | B15: Risk Assessment / Dynamic Recommendation Triggered from Formulas
A16: Liquidity Benchmark Check | B16: =IF(B5>=1.33,"LOW RISK: Current Ratio is " & TEXT(B5,"0.00") & " which meets the Tandon committee requirement of 1.33. Working capital liquidity is satisfactory.","HIGH RISK: Current Ratio is " & TEXT(B5,"0.00") & " which is below 1.33. Bank may review stock levels and promoter margin inflow.")
A17: Debt Repayment Capacity | B17: =IF(B8>=1.5,"STRONG COVENANT: The projected DSCR of " & TEXT(B8,"0.00") & " indicates robust repayment buffer. Comfortable servicing debt.","BORDERLINE CREDIT: Projected DSCR is " & TEXT(B8,"0.00") & ". Review repayment duration or add escrow lockup clauses.")
A18: MPBF Eligibility Check | B18: =IF('MPBF'!B8>0,"COMPLIANT: Max Permissible Bank Finance (MPBF) supports the required cash credit borrowing. Promoter NWC is satisfactory.","DEFICIENT: WCG is negative or promoter margin exceeds working capital gap. Additional equity contribution required.")
A19: Term Sanction Decision | B19: =IF(AND(B8>=1.4,B5>=1.2),"RECOMMENDED SANCTION: Financial projections show acceptable liquidity and repayment comfort. Sanction Term Loan and CC.","RE-EVALUATE: High credit risk due to weak liquidity (Current Ratio < 1.20) or tight debt service capacity (DSCR < 1.40). Review security collateral.")
