Workbook

Sheet Assumptions
A1: PROJECT REPORT METADATA & ASSUMPTIONS
A2: GOYAL FERTILIZER — Baseline Projection Configuration
A4: Entity Metadata
A5: Parameter | B5: Configuration Value
A6: Entity Name | B6: GOYAL FERTILIZER
A7: PAN | B7: AAKHG2303N1Z7
A8: Constitution | B8: Hindu Undivided Family (HUF)
A9: Nature of Business | B9: SUPPLIER OF FERTILIZER AND SEEDS AND PESTICIDES
A10: Purpose of Loan | B10: Required for Working Capital
A11: Moratorium Period (Months) | B11: 120
A12: Repayment Period (Months) | B12: 120
A15: Financial Model Drivers
A16: Growth & Cost Driver | B16: FY 2025-26 | C16: FY 2026-27 | D16: FY 2027-28 | E16: FY 2028-29 | F16: FY 2029-30
A17: Revenue Growth % (YoY) | B17: 0 | C17: 0.5 | D17: 0.5 | E17: 0 | F17: 0
A18: Raw Material Cost % of Sales | B18: 0.6 | C18: 0.6 | D18: 0.6 | E18: 0 | F18: 0
A19: Other Expenses % of Sales | B19: 0.12 | C19: 0.088 | D19: 0.0645333 | E19: 0.0645333 | F19: 0.0645333
A20: Corporate Income Tax Rate % | B20: 0.3 | C20: 0.3 | D20: 0.3 | E20: 0 | F20: 0
A21: Fixed Assets Depreciation Rate (WDV) | B21: 0.15 | C21: 0.15 | D21: 0.15 | E21: 0 | F21: 0
A22: Term Loan Interest Rate (per Annum) | B22: 0.095 | C22: 0.095 | D22: 0.095 | E22: 0.095 | F22: 0.095
A23: Receivable Days (Debtors) | B23: 45 | C23: 45 | D23: 45 | E23: 45 | F23: 45
A24: Stock Days (Inventory) | B24: 60 | C24: 60 | D24: 60 | E24: 60 | F24: 60
A25: Payable Days (Creditors) | B25: 30 | C25: 30 | D25: 30 | E25: 30 | F25: 30

Sheet Project Details
A1: PROJECT COST & MEANS OF FINANCE (₹)
A2: Greenfield Project Valuation & Funding Allocation
A4: Cost of Project Breakup
A5: Component | B5: Amount (₹) | C5: Percentage (%)
A6: Working Capital Margin | B6: 15000000 | C6: 1
A7: Total | B7: =SUM(B6:B6) | C7: =SUM(C6:C6)
A9: Means of Finance
A10: Source of Funding | B10: Amount (₹) | C10: Percentage (%)
A11: Term Loan | B11: 15000000 | C11: 1
A12: Total | B12: =SUM(B11:B11) | C12: =SUM(C11:C11)
A14: Debt-Equity Ratio | B14: —:1

Sheet Amortization
A1: TERM LOAN REPAYMENT SCHEDULE (₹)
A2: Amortization Table for ₹1.50 Crore Facility at 9.5% p.a.
A4: Year-wise Term Loan Schedule
A5: Year | B5: Opening Balance | C5: EMI Payments | D5: Principal Repayment | E5: Interest Accrued | F5: Closing Balance
A6: 1 | B6: 15000000 | C6: 0 | D6: 0 | E6: 1425000 | F6: 15000000
A7: 2 | B7: 15000000 | C7: 0 | D7: 0 | E7: 1425000 | F7: 15000000
A8: 3 | B8: 15000000 | C8: 0 | D8: 0 | E8: 1425000 | F8: 15000000
A9: 4 | B9: 15000000 | C9: 0 | D9: 0 | E9: 1425000 | F9: 15000000
A10: 5 | B10: 15000000 | C10: 0 | D10: 0 | E10: 1425000 | F10: 15000000
A11: 6 | B11: 15000000 | C11: 0 | D11: 0 | E11: 1425000 | F11: 15000000
A12: 7 | B12: 15000000 | C12: 0 | D12: 0 | E12: 1425000 | F12: 15000000
A13: 8 | B13: 15000000 | C13: 0 | D13: 0 | E13: 1425000 | F13: 15000000
A14: 9 | B14: 15000000 | C14: 0 | D14: 0 | E14: 1425000 | F14: 15000000
A15: 10 | B15: 15000000 | C15: 0 | D15: 0 | E15: 1425000 | F15: 15000000
A16: Total | C16: =SUM(C6:C15) | D16: =SUM(D6:D15) | E16: =SUM(E6:E15)

Sheet Depreciation
A1: FIXED ASSETS & DEPRECIATION SCHEDULE (₹)
A2: Project Cost Valuation & WDV Depreciation Forecast
A4: Project Asset Block & Annual Depreciation
A5: Particulars | B5: FY 2025-26 | C5: FY 2026-27 | D5: FY 2027-28 | E5: FY 2028-29 | F5: FY 2029-30
A6: Opening Fixed Assets (Gross Block) | B6: =0.0 | C6: =B9 | D6: =C9 | E6: =D9 | F6: =E9
A7: Additions (Project Cost) | B7: 15000000 | C7: 0 | D7: 0 | E7: 0 | F7: 0
A8: Deletions | B8: 0 | C8: 0 | D8: 0 | E8: 0 | F8: 0
A9: Closing Gross Block | B9: =B6+B7-B8 | C9: =C6+C7-C8 | D9: =D6+D7-D8 | E9: =E6+E7-E8 | F9: =F6+F7-F8
A10: Depreciation (WDV method) | B10: =B9*Assumptions!B22 | C10: =B11*Assumptions!C22 | D10: =C11*Assumptions!D22 | E10: =D11*Assumptions!E22 | F10: =E11*Assumptions!F22
A11: Closing Net Fixed Assets Block | B11: =B9-B10 | C11: =B11+C7-C8-C10 | D11: =C11+D7-D8-D10 | E11: =D11+E7-E8-E10 | F11: =E11+F7-F8-F10

Sheet Profit & Loss
A1: COMPARATIVE STATEMENT OF PROFIT & LOSS (₹)
A2: 5-Year Financial Revenue & Profitability Projections
A4: Particulars | B4: FY 2025-26 | C4: FY 2026-27 | D4: FY 2027-28 | E4: FY 2028-29 | F4: FY 2029-30
A5: Revenue from Net Sales | B5: 100000000 | C5: =B5*(1+Assumptions!C18) | D5: =C5*(1+Assumptions!D18) | E5: =D5*(1+Assumptions!E18) | F5: =E5*(1+Assumptions!F18)
A6: Other Income | B6: 0 | C6: 0 | D6: 0 | E6: 0 | F6: 0
A7: Total Revenue | B7: =B5+B6 | C7: =C5+C6 | D7: =D5+D6 | E7: =E5+E6 | F7: =F5+F6
A8: Less: Cost of Materials Consumed | B8: =B5*Assumptions!B19 | C8: =C5*Assumptions!C19 | D8: =D5*Assumptions!D19 | E8: =E5*Assumptions!E19 | F8: =F5*Assumptions!F19
A9: Less: Employee Benefits Expense | B9: 0 | C9: 0 | D9: 0 | E9: 0 | F9: 0
A10: Less: Other Operating Expenses | B10: =B5*Assumptions!B20 | C10: =C5*Assumptions!C20 | D10: =D5*Assumptions!D20 | E10: =E5*Assumptions!E20 | F10: =F5*Assumptions!F20
A11: Total Operating Expenses | B11: =B8+B9+B10 | C11: =C8+C9+C10 | D11: =D8+D9+D10 | E11: =E8+E9+E10 | F11: =F8+F9+F10
A12: Earnings before Interest, Tax, Dep & Amort (EBITDA) | B12: =B7-B11 | C12: =C7-C11 | D12: =D7-D11 | E12: =E7-E11 | F12: =F7-F11
A13: EBITDA Margin % | B13: =B12/B5 | C13: =C12/C5 | D13: =D12/D5 | E13: =E12/E5 | F13: =F12/F5
A14: Less: Depreciation & Amortization | B14: =Depreciation!B10 | C14: =Depreciation!C10 | D14: =Depreciation!D10 | E14: =Depreciation!E10 | F14: =Depreciation!F10
A15: Operating Profit (EBIT) | B15: =B12-B14 | C15: =C12-C14 | D15: =D12-D14 | E15: =E12-E14 | F15: =F12-F14
A16: Less: Term Loan Interest Expenses | B16: ='Balance Sheet'!B11*Assumptions!B23 | C16: ='Balance Sheet'!B11*Assumptions!C23 | D16: ='Balance Sheet'!C11*Assumptions!D23 | E16: 0 | F16: 0
A17: Profit Before Taxes (PBT) | B17: =B15-B16 | C17: =C15-C16 | D17: =D15-D16 | E17: =E15-E16 | F17: =F15-F16
A18: Less: Income Tax Provision | B18: =IF(B17>0,B17*Assumptions!B21,0) | C18: =IF(C17>0,C17*Assumptions!C21,0) | D18: =IF(D17>0,D17*Assumptions!D21,0) | E18: 0 | F18: 0
A19: Net Profit After Tax (PAT) | B19: =B17-B18 | C19: =C17-C18 | D19: =D17-D18 | E19: =E17-E18 | F19: =F17-F18
A20: PAT Margin % | B20: =B19/B5 | C20: =C19/C5 | D20: =D19/D5 | E20: =E19/E5 | F20: =F19/F5
A21: Cash Profit (PAT + Depreciation) | B21: =B19+B14 | C21: =C19+C14 | D21: =D19+D14 | E21: =E19+E14 | F21: =F19+F14

Sheet Balance Sheet
A1: COMPARATIVE BALANCE SHEET (₹)
A2: Projected Sources & Applications of Corporate Capital Funds
A4: Particulars | B4: FY 2025-26 | C4: FY 2026-27 | D4: FY 2027-28 | E4: FY 2028-29 | F4: FY 2029-30
A5: EQUITY & LIABILITIES
A6: Shareholders' Funds
A7: - Share Capital | B7: 0 | C7: 0 | D7: 0 | E7: 0 | F7: 0
A8: - Reserves & Surplus (Retained Earnings) | B8: ='Profit & Loss'!B19 | C8: =B8+'Profit & Loss'!C19 | D8: =C8+'Profit & Loss'!D19 | E8: =D8+'Profit & Loss'!E19 | F8: =E8+'Profit & Loss'!F19
A9: Tangible Net Worth (A) | B9: =B7+B8 | C9: =C7+C8 | D9: =D7+D8 | E9: =E7+E8 | F9: =F7+F8
A10: Non-Current Liabilities
A11: - Long-Term Borrowings (Term Loan) | B11: 15000000 | C11: =B11*0.9 | D11: =C11*0.9 | E11: =D11*0.9 | F11: =E11*0.9
A12: Non-Current Liabilities (B) | B12: =B11 | C12: =C11 | D12: =D11 | E12: =E11 | F12: =F11
A13: Current Liabilities
A14: - Short-Term Borrowings (Cash Credit) | B14: 0 | C14: 0 | D14: 0 | E14: 0 | F14: 0
A15: - Trade Payables (Sundry Creditors) | B15: ='Profit & Loss'!B8*Assumptions!B26/365 | C15: ='Profit & Loss'!C8*Assumptions!C26/365 | D15: ='Profit & Loss'!D8*Assumptions!D26/365 | E15: =D15 | F15: =E15
A16: - Other Current Liabilities | B16: 0 | C16: 0 | D16: 0 | E16: 0 | F16: 0
A17: Current Liabilities (C) | B17: =B14+B15+B16 | C17: =C14+C15+C16 | D17: =D14+D15+D16 | E17: =E14+E15+E16 | F17: =F14+F15+F16
A18: TOTAL OUTSIDE LIABILITIES (B + C) | B18: =B12+B17 | C18: =C12+C17 | D18: =D12+D17 | E18: =E12+E17 | F18: =F12+F17
A19: TOTAL EQUITY & LIABILITIES (A + B + C) | B19: =B9+B12+B17 | C19: =C9+C12+C17 | D19: =D9+D12+D17 | E19: =E9+E12+E17 | F19: =F9+F12+F17
A20: APPLICATION & ASSETS
A21: Non-Current Assets
A22: - Net Fixed Assets Block (WDV) | B22: =Depreciation!B11 | C22: =Depreciation!C11 | D22: =Depreciation!D11 | E22: =Depreciation!E11 | F22: =Depreciation!F11
A23: - Non-Current Investments | B23: 0 | C23: 0 | D23: 0 | E23: 0 | F23: 0
A24: Non-Current Assets (D) | B24: =B22+B23 | C24: =C22+C23 | D24: =D22+D23 | E24: =E22+E23 | F24: =F22+F23
A25: Current Assets
A26: - Inventories / Stock-in-Hand | B26: ='Profit & Loss'!B8*Assumptions!B25/365 | C26: ='Profit & Loss'!C8*Assumptions!C25/365 | D26: ='Profit & Loss'!D8*Assumptions!D25/365 | E26: =D26 | F26: =E26
A27: - Trade Receivables (Sundry Debtors) | B27: ='Profit & Loss'!B5*Assumptions!B24/365 | C27: ='Profit & Loss'!C5*Assumptions!C24/365 | D27: ='Profit & Loss'!D5*Assumptions!D24/365 | E27: ='Profit & Loss'!E5*Assumptions!E24/365 | F27: ='Profit & Loss'!F5*Assumptions!F24/365
A28: - Cash and Bank Balances | B28: ='Cash Flow'!B23 | C28: ='Cash Flow'!C23 | D28: ='Cash Flow'!D23 | E28: ='Cash Flow'!E23 | F28: ='Cash Flow'!F23
A29: - Other Current Assets | B29: 0 | C29: 0 | D29: 0 | E29: 0 | F29: 0
A30: - Balancing Debit Account | B30: =B19-B24-B26-B27-B28-B29 | C30: =C19-C24-C26-C27-C28-C29 | D30: =D19-D24-D26-D27-D28-D29 | E30: =E19-E24-E26-E27-E28-E29 | F30: =F19-F24-F26-F27-F28-F29
A31: Total Current Assets (E) | B31: =B26+B27+B28+B29+B30 | C31: =C26+C27+C28+C29+C30 | D31: =D26+D27+D28+D29+D30 | E31: =E26+E27+E28+E29+E30 | F31: =F26+F27+F28+F29+F30
A32: TOTAL ASSETS (D + E) | B32: =B24+B31 | C32: =C24+C31 | D32: =D24+D31 | E32: =E24+E31 | F32: =F24+F31
A33: Balance Sheet Reconciliation Check | B33: =B32-B19 | C33: =C32-C19 | D33: =D32-D19 | E33: =E32-E19 | F33: =F32-F19

Sheet MPBF
A1: WORKING CAPITAL MPBF ASSESSMENT (₹)
A2: Tandon Committee (Second Method) Calculations
A4: Maximum Permissible Bank Finance
A5: Particulars | B5: FY 2025-26 | C5: FY 2026-27 | D5: FY 2027-28 | E5: FY 2028-29 | F5: FY 2029-30
A6: Total Current Assets (TCA) | B6: ='Balance Sheet'!B31-'Balance Sheet'!B30 | C6: ='Balance Sheet'!C31-'Balance Sheet'!C30 | D6: ='Balance Sheet'!D31-'Balance Sheet'!D30 | E6: ='Balance Sheet'!E31-'Balance Sheet'!E30 | F6: ='Balance Sheet'!F31-'Balance Sheet'!F30
A7: Less: Current Liabilities (excluding bank borrowings) | B7: ='Balance Sheet'!B15+'Balance Sheet'!B16 | C7: ='Balance Sheet'!C15+'Balance Sheet'!C16 | D7: ='Balance Sheet'!D15+'Balance Sheet'!D16 | E7: ='Balance Sheet'!E15+'Balance Sheet'!E16 | F7: ='Balance Sheet'!F15+'Balance Sheet'!F16
A8: Working Capital Gap (WCG) | B8: =B6-B7 | C8: =C6-C7 | D8: =D6-D7 | E8: =E6-E7 | F8: =F6-F7
A9: Less: 25% of TCA as Margin (Promoter Contribution) | B9: =0.25*B6 | C9: =0.25*C6 | D9: =0.25*D6 | E9: =0.25*E6 | F9: =0.25*F6
A10: Maximum Permissible Bank Finance (MPBF) | B10: =B8-B9 | C10: =C8-C9 | D10: =D8-D9 | E10: =E8-E9 | F10: =F8-F9

Sheet Drawing Power
A1: CASH CREDIT DRAWING POWER STATEMENT (₹)
A2: Margins & Drawing Power Allocation against Inventory & Debtors
A4: Drawing Power Calculations
A5: Particulars | B5: FY 2025-26 | C5: FY 2026-27 | D5: FY 2027-28 | E5: FY 2028-29 | F5: FY 2029-30
A6: Total Inventories / Stock | B6: ='Balance Sheet'!B26 | C6: ='Balance Sheet'!C26 | D6: ='Balance Sheet'!D26 | E6: ='Balance Sheet'!E26 | F6: ='Balance Sheet'!F26
A7: Total Debtors / Receivables | B7: ='Balance Sheet'!B27 | C7: ='Balance Sheet'!C27 | D7: ='Balance Sheet'!D27 | E7: ='Balance Sheet'!E27 | F7: ='Balance Sheet'!F27
A8: Total Security Cover Offered | B8: =B6+B7 | C8: =C6+C7 | D8: =D6+D7 | E8: =E6+E7 | F8: =F6+F7
A9: Less: Trade Creditors (Sundry Creditors) | B9: ='Balance Sheet'!B15 | C9: ='Balance Sheet'!C15 | D9: ='Balance Sheet'!D15 | E9: ='Balance Sheet'!E15 | F9: ='Balance Sheet'!F15
A10: Net Paid-up Valuation | B10: =B8-B9 | C10: =C8-C9 | D10: =D8-D9 | E10: =E8-E9 | F10: =F8-F9
A11: Drawing Power (allowed up to 75% of net value) | B11: =B10*0.75 | C11: =C10*0.75 | D11: =D10*0.75 | E11: =E10*0.75 | F11: =F10*0.75

Sheet Cash Flow
A1: PROJECTED CASH FLOW STATEMENT (₹)
A2: Sources and Applications of Corporate Business Funds
A4: Particulars | B4: FY 2025-26 | C4: FY 2026-27 | D4: FY 2027-28 | E4: FY 2028-29 | F4: FY 2029-30
A5: A. CASH FLOW FROM OPERATING ACTIVITIES
A6: - Net Profit After Tax (PAT) | B6: ='Profit & Loss'!B19 | C6: ='Profit & Loss'!C19 | D6: ='Profit & Loss'!D19 | E6: ='Profit & Loss'!E19 | F6: ='Profit & Loss'!F19
A7: - Add: Depreciation & Amortization | B7: ='Profit & Loss'!B14 | C7: ='Profit & Loss'!C14 | D7: ='Profit & Loss'!D14 | E7: ='Profit & Loss'!E14 | F7: ='Profit & Loss'!F14
A8: - (Increase)/Decrease in Sundry Debtors | B8: 0 | C8: =-('Balance Sheet'!C27-'Balance Sheet'!B27) | D8: =-('Balance Sheet'!D27-'Balance Sheet'!C27) | E8: =-('Balance Sheet'!E27-'Balance Sheet'!D27) | F8: =-('Balance Sheet'!F27-'Balance Sheet'!E27)
A9: - (Increase)/Decrease in Inventories | B9: 0 | C9: =-('Balance Sheet'!C26-'Balance Sheet'!B26) | D9: =-('Balance Sheet'!D26-'Balance Sheet'!C26) | E9: =-('Balance Sheet'!E26-'Balance Sheet'!D26) | F9: =-('Balance Sheet'!F26-'Balance Sheet'!E26)
A10: - Increase/(Decrease) in Trade Creditors | B10: 0 | C10: ='Balance Sheet'!C15-'Balance Sheet'!B15 | D10: ='Balance Sheet'!D15-'Balance Sheet'!C15 | E10: ='Balance Sheet'!E15-'Balance Sheet'!D15 | F10: ='Balance Sheet'!F15-'Balance Sheet'!E15
A11: Net Cash Generated from Operations (A) | B11: =SUM(B6:B10) | C11: =SUM(C6:C10) | D11: =SUM(D6:D10) | E11: =SUM(E6:E10) | F11: =SUM(F6:F10)
A12: B. CASH FLOW FROM INVESTING ACTIVITIES
A13: - Capital Expenditure / Project Cost | B13: -15000000 | C13: 0 | D13: 0 | E13: 0 | F13: 0
A14: Net Cash Used in Investing Activities (B) | B14: =B13 | C14: =C13 | D14: =D13 | E14: =E13 | F14: =F13
A15: C. CASH FLOW FROM FINANCING ACTIVITIES
A16: - Term Loan Facility Disbursed | B16: 15000000 | C16: 0 | D16: 0 | E16: 0 | F16: 0
A17: - Change in Borrowings (Repayments) | B17: 0 | C17: ='Balance Sheet'!C11-'Balance Sheet'!B11 | D17: ='Balance Sheet'!D11-'Balance Sheet'!C11 | E17: ='Balance Sheet'!E11-'Balance Sheet'!D11 | F17: ='Balance Sheet'!F11-'Balance Sheet'!E11
A18: - Interest on Term Loan Paid | B18: =-'Profit & Loss'!B16 | C18: =-'Profit & Loss'!C16 | D18: =-'Profit & Loss'!D16 | E18: 0 | F18: 0
A19: Net Cash from Financing Activities (C) | B19: =SUM(B16:B18) | C19: =SUM(C16:C18) | D19: =SUM(D16:D18) | E19: =SUM(E16:E18) | F19: =SUM(F16:F18)
A20: D. SUMMARY OF CASH POSITION
A21: - Net Increase in Cash (A + B + C) | B21: =B11+B14+B19 | C21: =C11+C14+C19 | D21: =D11+D14+D19 | E21: =E11+E14+E19 | F21: =F11+F14+F19
A22: - Opening Cash and Bank Balance | B22: 0 | C22: =B23 | D22: =C23 | E22: =D23 | F22: =E23
A23: - Closing Cash and Bank Balance | B23: 2017226 | C23: 8101976 | D23: 18262039 | E23: 60358039 | F23: 1.0245404e+08

Sheet Ratios
A1: FINANCIAL RATIO ANALYSIS DASHBOARD
A2: Key Risk, Leverage, & Profitability Ratios vs Banking Benchmarks
A4: Core Banking Financial Ratios
A5: Ratio / Indicator | B5: Formula | C5: Banking Norm | D5: FY 2025-26 | E5: FY 2026-27 | F5: FY 2027-28 | G5: FY 2028-29 | H5: FY 2029-30
A6: Current Ratio | B6: TCA / TCL | C6: >= 1.33 | D6: ='Balance Sheet'!B31/'Balance Sheet'!B17 | E6: ='Balance Sheet'!C31/'Balance Sheet'!C17 | F6: ='Balance Sheet'!D31/'Balance Sheet'!D17 | G6: ='Balance Sheet'!E31/'Balance Sheet'!E17 | H6: ='Balance Sheet'!F31/'Balance Sheet'!F17
A7: Quick Ratio | B7: (TCA-Stock)/TCL | C7: >= 1.00 | D7: =('Balance Sheet'!B31-'Balance Sheet'!B30-'Balance Sheet'!B26)/'Balance Sheet'!B17 | E7: =('Balance Sheet'!C31-'Balance Sheet'!C30-'Balance Sheet'!C26)/'Balance Sheet'!C17 | F7: =('Balance Sheet'!D31-'Balance Sheet'!D30-'Balance Sheet'!D26)/'Balance Sheet'!D17 | G7: =('Balance Sheet'!E31-'Balance Sheet'!E30-'Balance Sheet'!E26)/'Balance Sheet'!E17 | H7: =('Balance Sheet'!F31-'Balance Sheet'!F30-'Balance Sheet'!F26)/'Balance Sheet'!F17
A8: Debt-Equity Ratio | B8: Long Term Debt / TNW | C8: <= 2.00 | D8: ='Balance Sheet'!B11/'Balance Sheet'!B9 | E8: ='Balance Sheet'!C11/'Balance Sheet'!C9 | F8: ='Balance Sheet'!D11/'Balance Sheet'!D9 | G8: ='Balance Sheet'!E11/'Balance Sheet'!E9 | H8: ='Balance Sheet'!F11/'Balance Sheet'!F9
A9: TOL / TNW Ratio | B9: Total Outside Liab / TNW | C9: <= 3.00 | D9: ='Balance Sheet'!B18/'Balance Sheet'!B9 | E9: ='Balance Sheet'!C18/'Balance Sheet'!C9 | F9: ='Balance Sheet'!D18/'Balance Sheet'!D9 | G9: ='Balance Sheet'!E18/'Balance Sheet'!E9 | H9: ='Balance Sheet'!F18/'Balance Sheet'!F9
A10: Debt Service Coverage Ratio (DSCR) | B10: (PAT+Dep+Int)/(Prin+Int) | C10: >= 1.25 | D10: =IF(('Amortization'!D6+'Profit & Loss'!B16)=0,0,('Profit & Loss'!B19+'Profit & Loss'!B14+'Profit & Loss'!B16)/('Amortization'!D6+'Profit & Loss'!B16)) | E10: =IF(('Amortization'!D7+'Profit & Loss'!C16)=0,0,('Profit & Loss'!C19+'Profit & Loss'!C14+'Profit & Loss'!C16)/('Amortization'!D7+'Profit & Loss'!C16)) | F10: =IF(('Amortization'!D8+'Profit & Loss'!D16)=0,0,('Profit & Loss'!D19+'Profit & Loss'!D14+'Profit & Loss'!D16)/('Amortization'!D8+'Profit & Loss'!D16)) | G10: =IF(('Amortization'!D9+'Profit & Loss'!E16)=0,0,('Profit & Loss'!E19+'Profit & Loss'!E14+'Profit & Loss'!E16)/('Amortization'!D9+'Profit & Loss'!E16)) | H10: =IF(('Amortization'!D10+'Profit & Loss'!F16)=0,0,('Profit & Loss'!F19+'Profit & Loss'!F14+'Profit & Loss'!F16)/('Amortization'!D10+'Profit & Loss'!F16))
A11: Interest Coverage Ratio | B11: EBIT / Interest | C11: >= 2.00 | D11: =IF('Profit & Loss'!B16=0,0,'Profit & Loss'!B15/'Profit & Loss'!B16) | E11: =IF('Profit & Loss'!C16=0,0,'Profit & Loss'!C15/'Profit & Loss'!C16) | F11: =IF('Profit & Loss'!D16=0,0,'Profit & Loss'!D15/'Profit & Loss'!D16) | G11: =IF('Profit & Loss'!E16=0,0,'Profit & Loss'!E15/'Profit & Loss'!E16) | H11: =IF('Profit & Loss'!F16=0,0,'Profit & Loss'!F15/'Profit & Loss'!F16)
A12: Gross Profit Margin % | B12: (Revenue-RM Cost)/Revenue | C12: > 30% | D12: =('Profit & Loss'!B5-'Profit & Loss'!B8)/'Profit & Loss'!B5 | E12: =('Profit & Loss'!C5-'Profit & Loss'!C8)/'Profit & Loss'!C5 | F12: =('Profit & Loss'!D5-'Profit & Loss'!D8)/'Profit & Loss'!D5 | G12: =('Profit & Loss'!E5-'Profit & Loss'!E8)/'Profit & Loss'!E5 | H12: =('Profit & Loss'!F5-'Profit & Loss'!F8)/'Profit & Loss'!F5
A13: EBITDA Margin % | B13: EBITDA / Sales | C13: > 10% | D13: ='Profit & Loss'!B13 | E13: ='Profit & Loss'!C13 | F13: ='Profit & Loss'!D13 | G13: ='Profit & Loss'!E13 | H13: ='Profit & Loss'!F13
A14: PAT Margin % | B14: PAT / Sales | C14: > 5% | D14: ='Profit & Loss'!B20 | E14: ='Profit & Loss'!C20 | F14: ='Profit & Loss'!D20 | G14: ='Profit & Loss'!E20 | H14: ='Profit & Loss'!F20

Sheet Sensitivity
A1: SENSITIVITY ANALYSIS STRESS TESTS
A2: Impact of Adverse Revenue and Cost Scenarios on Debt Service (DSCR)
A4: DSCR Stress Scenarios
A5: Scenario | B5: Assumption | C5: Projected DSCR | D5: Stressed DSCR | E5: Assessment
A6: Revenue Decline 10% | B6: Sales drop by 10% | C6: 0 | D6: 0 | E6: Stressed
A7: Revenue Decline 20% | B7: Sales drop by 20% | C7: 0 | D7: 0 | E7: Stressed
A8: Cost Increase 10% | B8: Material costs rise 10% | C8: 0 | D8: 0 | E8: Stressed
A9: Combined Stress | B9: Revenue -10%, Cost +5% | C9: 0 | D9: 0 | E9: Stressed
